nostats/__init__.py
nostats/core/__init__.py
nostats/datasets/__init__.py
nostats/models/__init__.py
nostats/utils/__init__.py
nostats/utils/convertor.py
nostats/utils/device_parms.py
nostats/utils/rich_style.py
nostats/utils/test-path.py
nostats/utils/config/rich_style_config.yaml
nostats/viz/__init__.py
nostats-0.1.1.dist-info/licenses/LICENSE
nostats-0.1.1.dist-info/METADATA
nostats-0.1.1.dist-info/WHEEL
nostats-0.1.1.dist-info/top_level.txt
nostats-0.1.1.dist-info/RECORD
