Metadata-Version: 2.4
Name: nostats
Version: 0.1.1
Summary: A package to learn Statistics
Author-email: NoVarYe <jidijam.olk@outlook.com>
Project-URL: homepage, https://www.nowisdoms.xyz/
Project-URL: repository, https://github.com/No4Var2Ye/LSTATISTICS
Keywords: Statistics
Classifier: Programming Language :: Python :: 3
Classifier: License :: OSI Approved :: MIT License
Classifier: Operating System :: OS Independent
Requires-Python: >=3.10
License-File: LICENSE
Requires-Dist: pyyaml==6.0.2
Requires-Dist: matplotlib==3.10.3
Requires-Dist: pandas==2.3.0
Requires-Dist: plotly==6.2.0
Requires-Dist: rich==14.0.0
Requires-Dist: seaborn==0.13.2
Requires-Dist: nvidia-ml-py>=12.0.0
Requires-Dist: psutil==7.0.0
Requires-Dist: cairosvg
Dynamic: license-file
